templates/__init__.py
templates/base.py
templates/demo.py
templates/bootstrap/__init__.py
templates/bootstrap/base.py
templates/bootstrap/bootstrap.min.css
templates/bootstrap/bootstrap.min.js
templates/bootstrap/jquery-3.2.1.slim.min.js
templates/bootstrap/jumbotron.py
templates/bootstrap/popper.min.js
templates/bootstrap/starter.py
templates-0.0.5.dist-info/METADATA
templates-0.0.5.dist-info/RECORD
templates-0.0.5.dist-info/WHEEL
templates-0.0.5.dist-info/top_level.txt
